devibe/__init__.py
devibe/__main__.py
devibe/cli.py
devibe/parsers.py
devibe/remover.py
devibe/rules.py
devibe-0.1.0.dist-info/licenses/LICENSE
tests/__init__.py
tests/test_parsers.py
tests/test_remover.py
tests/test_rules.py
devibe-0.1.0.dist-info/METADATA
devibe-0.1.0.dist-info/WHEEL
devibe-0.1.0.dist-info/entry_points.txt
devibe-0.1.0.dist-info/top_level.txt
devibe-0.1.0.dist-info/RECORD
